{
  "project_info": {
    "project_number": "505898186912",
    "project_id": "fruit-hub-e90a3",
    "storage_bucket": "fruit-hub-e90a3.firebasestorage.app"
  },
  "client": [
    {
      "client_info": {
        "mobilesdk_app_id": "1:505898186912:android:7803fc343b653e99e231c5",
        "android_client_info": {
          "package_name": "com.example.fruits_hub"
        }
      },
      "oauth_client": [],
      "api_key": [
        {
          "current_key": "AIzaSyC2Ygv_uqke-IbUwzd1C2Id29DpaBAKVto"
        }
      ],
      "services": {
        "appinvite_service": {
          "other_platform_oauth_client": []
        }
      }
    }
  ],
  "configuration_version": "1"
}